entity/__init__.py
entity/cli.py
entity/client.py
entity/data.py
entity/exceptions.py
entity/settings.py
entity/version.py
moonstream_entity-0.0.5.dist-info/METADATA
moonstream_entity-0.0.5.dist-info/WHEEL
moonstream_entity-0.0.5.dist-info/entry_points.txt
moonstream_entity-0.0.5.dist-info/top_level.txt
moonstream_entity-0.0.5.dist-info/RECORD
